syengohelloworldpackage/__init__.py
syengohelloworldpackage-0.1.1.dist-info/WHEEL
syengohelloworldpackage-0.1.1.dist-info/METADATA
syengohelloworldpackage-0.1.1.dist-info/RECORD
